javalang/__init__.py
javalang/ast.py
javalang/javadoc.py
javalang/parse.py
javalang/parser.py
javalang/tokenizer.py
javalang/tree.py
javalang/util.py
javalang-0.13.0.dist-info/LICENSE.txt
javalang-0.13.0.dist-info/METADATA
javalang-0.13.0.dist-info/WHEEL
javalang-0.13.0.dist-info/top_level.txt
javalang-0.13.0.dist-info/RECORD
