Metadata-Version: 1.1
Name: javalang
Version: 0.13.0
Summary: Pure Python Java parser and tools
Home-page: http://github.com/c2nes/javalang
Author: Chris Thunes
Author-email: cthunes@brewtab.com
License: UNKNOWN
Platform: UNKNOWN
Classifier: Programming Language :: Python
Classifier: Development Status :: 4 - Beta
Classifier: Operating System :: OS Independent
Classifier: License :: OSI Approved :: MIT License
Classifier: Intended Audience :: Developers
Classifier: Topic :: Software Development :: Libraries
